{
  "hash": "31c1b384ef26ed7b784f25529d43635f",
  "result": {
    "engine": "knitr",
    "markdown": "---\ntitle: ATFM Delay Codes\nslug: atfm-delay-codes\n---\n\n::: {.cell}\n\n:::\n\n\nThe reason for the regulation is indicated by the responsible Flow Management Position [FMP](/acronym/fmp/).\n\nFor post-ops analysis individual delay codes can be included in a ATFM delay group. \n\n\n\n| REF LOC | REGU REASON CODE | REGU REASON NAME | REASON GROUP | ATTRIBUTE |\n|---------|------------------|------------------|--------------|-----------|\n|Airport|C|ATC Capacity|AD Capacity (ATC)|Airport / TMA|\n|Airport|S|ATC Staffing|AD Staffing (ATC)|Airport / TMA|\n|Airport|I|Industrial Action (ATC)|AD Disruptions (ATC)|Airport / TMA|\n|Airport|T|Equipment (ATC)|AD Disruptions (ATC)|Airport / TMA|\n|Airport|G|Aerodrome Capacity|AD Capacity|Airport / TMA|\n|Airport|M|Military Activity|AD Capacity|Airport / TMA|\n|Airport|R|ATC Routeing|AD Capacity|Airport / TMA|\n|Airport|V|Environmental Issues|AD Capacity|Airport / TMA|\n|Airport|A|Accident/Incident|AD Disruptions|Airport / TMA|\n|Airport|E|Aerodrome Services|AD Disruptions|Airport / TMA|\n|Airport|N|Industrial Action (non-ATC)|AD Disruptions|Airport / TMA|\n|Airport|NA|Not regulated/Not specified|AD Disruptions|Airport / TMA|\n|Airport|O|Other|AD Disruptions|Airport / TMA|\n|Airport|P|Special Event|AD Events|Airport / TMA|\n|Airport|D|De-icing|AD Weather|Airport / TMA|\n|Airport|W|Weather|AD Weather|Airport / TMA|\n|En route|C|ATC Capacity|ER Capacity (ATC)|En route|\n|En route|S|ATC Staffing|ER Staffing (ATC)|En route|\n|En route|I|Industrial Action (ATC)|ER Disruptions (ATC)|En route|\n|En route|T|Equipment (ATC)|ER Disruptions (ATC)|En route|\n|En route|G|Aerodrome Capacity|ER Capacity|En route|\n|En route|M|Military Activity|ER Capacity|En route|\n|En route|R|ATC Routeing|ER Capacity|En route|\n|En route|V|Environmental Issues|ER Capacity|En route|\n|En route|A|Accident/Incident|ER Disruptions|En route|\n|En route|E|Aerodrome Services|ER Disruptions|En route|\n|En route|N|Industrial Action (non-ATC)|ER Disruptions|En route|\n|En route|NA|Not regulated/Not specified|ER Disruptions|En route|\n|En route|O|Other|ER Disruptions|En route|\n|En route|P|Special Event|ER Events|En route|\n|En route|D|De-icing|ER Weather|En route|\n|En route|W|Weather|ER Weather|En route|\n|na|NA|Not regulated/Not specified|ER Disruptions|En route|\n\n\n## See Also\n\n* [ATFM delay](/definition/atfm-delay/).\n* `{{% a_blank ectrl \"ATFCM Users Manual\" \"https://www.eurocontrol.int/publication/atfcm-users-manual\" %}}`{=html}.",
    "supporting": [
      "atfm-delay-codes_files"
    ],
    "filters": [
      "rmarkdown/pagebreak.lua"
    ],
    "includes": {},
    "engineDependencies": {},
    "preserve": {},
    "postProcess": true
  }
}